aceai/CHANGELOG.md
aceai/__init__.py
aceai/errors.py
aceai/event_bus.py
aceai/interface.py
aceai/models.py
aceai/py.typed
aceai/agent/__init__.py
aceai/agent/base.py
aceai/agent/context_manager.py
aceai/agent/events.py
aceai/agent/executor.py
aceai/helpers/delta_buffer.py
aceai/helpers/string.py
aceai/helpers/time.py
aceai/llm/__init__.py
aceai/llm/models.py
aceai/llm/openai.py
aceai/llm/service.py
aceai/tools/__init__.py
aceai/tools/_tool_sig.py
aceai/tools/base.py
aceai/tools/builtin_tools.py
aceai/tools/schema_generator.py
aceai-0.1.8.dist-info/METADATA
aceai-0.1.8.dist-info/WHEEL
aceai-0.1.8.dist-info/RECORD
