Metadata-Version: 2.4
Name: aceai
Version: 0.1.8
Summary: AI agent framework that delivers
Author-email: raceychan <raceychan@gmail.com>
Requires-Python: >=3.12
Requires-Dist: ididi>=1.8.4
Requires-Dist: msgspec>=0.20.0
Requires-Dist: opentelemetry-api>=1.39.1
Requires-Dist: typing-extensions>=4.15.0
Provides-Extra: otel
Requires-Dist: opentelemetry-exporter-otlp-proto-http>=1.39.1; extra == 'otel'
Requires-Dist: opentelemetry-sdk>=1.39.1; extra == 'otel'
